django_python3_ldap/__init__.py
django_python3_ldap/auth.py
django_python3_ldap/conf.py
django_python3_ldap/ldap.py
django_python3_ldap/tests.py
django_python3_ldap/utils.py
django_python3_ldap/management/__init__.py
django_python3_ldap/management/commands/__init__.py
django_python3_ldap/management/commands/ldap_clean_users.py
django_python3_ldap/management/commands/ldap_promote.py
django_python3_ldap/management/commands/ldap_sync_users.py
django_python3_ldap-0.16.1.dist-info/licenses/LICENSE
django_python3_ldap-0.16.1.dist-info/METADATA
django_python3_ldap-0.16.1.dist-info/WHEEL
django_python3_ldap-0.16.1.dist-info/top_level.txt
django_python3_ldap-0.16.1.dist-info/RECORD
