Metadata-Version: 2.4
Name: django-python3-ldap
Version: 0.16.1
Summary: Django LDAP user authentication backend for Python 3.
Home-page: https://github.com/etianen/django-python3-ldap
Author: Dave Hall
Author-email: dave@etianen.com
License: BSD
Classifier: Development Status :: 4 - Beta
Classifier: Environment :: Web Environment
Classifier: Intended Audience :: Developers
Classifier: License :: OSI Approved :: BSD License
Classifier: Operating System :: OS Independent
Classifier: Programming Language :: Python
Classifier: Programming Language :: Python :: 3.9
Classifier: Programming Language :: Python :: 3.10
Classifier: Programming Language :: Python :: 3.11
Classifier: Programming Language :: Python :: 3.12
Classifier: Framework :: Django
License-File: LICENSE
Requires-Dist: django>=4.2
Requires-Dist: asgiref>=2.0.0
Requires-Dist: ldap3<3,>=2.5
Requires-Dist: pyasn1<0.7,>=0.4.6
Dynamic: author
Dynamic: author-email
Dynamic: classifier
Dynamic: description
Dynamic: home-page
Dynamic: license
Dynamic: license-file
Dynamic: requires-dist
Dynamic: summary
